tarch/__init__.py
tarch/train_test_split.py
tarch/zadachki.py
torche/__init__.py
torche/train_test_split.py
torche-0.0.3.dist-info/METADATA
torche-0.0.3.dist-info/WHEEL
torche-0.0.3.dist-info/top_level.txt
torche-0.0.3.dist-info/RECORD
