Metadata-Version: 2.1
Name: torche
Version: 0.0.3
Summary: ///
Home-page: https://github.com/Vika-K228
Author: lalala
Author-email: vikki.flover@gmail.com
Requires-Python: >=3.0
